{
    "general_info": {
        "name": "Bar Pacto Secreto",
        "township":"Diez de Octubre",
        "address": "Calzada de 10 de Octubre #417 entre Calzada de Luyano y San Nicolas, Diez de Octubre",
        "local":"Bar-Cafeteria",
        "open":"12:00",
        "close":"15:00",
        "days_of_week":[],
        "sector":"",
        "capability":null,
        "social_network":[{"facebook": "https://www.facebook.com/profile.php?id=100091382520199","phone_number": "76388121"}],
        "years":null
        
    },
    "economy": {
        "payment_methods":["efectivo","transferencia"],
        "online_reservation":null,
        "tips_included":null,
        "delivery":null
    },
    "food": {
        "menu": {
            
            "appetizers":{
                "appetizers_list":["Tostones naturales","Fritura de malanga","Croquetas de la casa","Bolitas de carne picantes","Bolitas de queso","Tostones rellenos jamon","Tostones rellenos chorizo","Tostones rellenos atun","Tostones rellenos mixtos"],
                "appetizers_price":[300,470,500,650,780,650,650,750,700]
            },
            "garnishes":{
                "garnishes_list":[],
                "garnishes_price":[]
            },
            "hamburger":{
                "hamburger_list":[],
                "hamburger_price":[]
            },
            "bread":{
                "bread_list":[],
                "bread_price":[]
            },
            "main":{
                "main_list":["Pollo troceado","Pollo a la Juliana", "Bistec de cerdo encebollado","Masas al gusto"],
                "main_price":[1200,1300,1400,1600]
            },
            "sea_food":{
                "sea_food_list":[],
                "sea_food_price":[]
            },
            "pasta":{
                "pasta_list":[],
                "pasta_price":[]
            },
            "pizza":{
                "pizza_list":[],
                "pizza_price":[]
            },
            "adds":{
                "adds_list":[],
                "adds_price":[]
            },
            
            "dessert":{
                "dessert_list":[],
                "dessert_price":[]
            },
            "drinks":{
                "alcohol_list":["Canchanchara","Mojito","Daiquiri","Cubalibre","Cubata","Cubaquito","Tom Collins","Caipirosca","Caipirinha","Caipira","Vodka Tonic","Vodka Tonic Plus","Gin Tonic", "Gin Tonic Plus","Long Island","Screwdriver","Sangria","Old Fashion","Old Fashion Plus","Blue Lagoon","Blue Hawaii","Bloody Mary","Pinna Colada","Pinna Colada S/A","Pacto Secreto","Cerveza Cristal","Cervezas Importadas","Cerveza Corona","Jarra Dispensada(500 ml)","Termo Dispensada(3L)","Michelada","Chelada","Santiago Tradicion","Santiago 3 Annos","Santiago 8 Annos","Santiago 12 Annos","H. Club Especial","H. Club Reserva","H. Club 7 Annos","H. Club 3 de Maestro","H. Club 15 Annos","Bailey","Tequila Rose","Igor","Absolut","Meukow","Courvoisier","Hennessey","Beefeater","Gordon","Bombay","Tanqueray","Shot 3limador","Shot Hornitos","Don Julio Reposado","Don Julio Annejo","Olmeca Blanco","Olmeca Reposado","Ballantines","Ballantines 12","Jameson","Jack Daniels","Chivas Regal 12","Chivas Regal Extra","J W Red Label","J W Black Label","J W Swing","J W Select Cosk","J W The Spice Road","J W Island Green","J W Platinum Edited Limited"],
                "alcohol_price":[450,400,400,480,480,500,400,650,650,450,400,680,500,750,1100,450,600,500,1000,500,500,550,600,500,1500,320,280,400,400,2000,500,300,150,320,350,700,1200,350,400,400,800,2000,900,1200,300,600,700,700,900,350,450,500,600,500,700,1800,1000,500,500,650,500,700,550,700,800,1000,650,900,900,1500,1500,2000,2500],
                "infusions_list":[],
                "infusions_price":[],
                "non_alcoholic_list":["Agua natural","Limonada Frappe","Refrescos Importados","Maltas Importadas","Malta Bucanero","Jugos Naturales","Batidos Frutas","Red Bull"],
                "non_alcoholic_price":[200,250,250,250,400,250,380]
            }
        },
        "popular_food":[],
        "popular_drink":[],
        "food_especialization":["cubana", "comida rapida"],
        "house_especiality":["cubana", "comida rapida"]
    },
    "social": {
        "kids_seat":null,
        "blackout_alternatives":null,
        "entertainment":[],
        "peak_hour":[],
        "tourism":null,
        "pets":null,
        "bathroom":null,
        "heated":null
    }
}