{
    "general_info": {
        "name": "La_Terraza_del_Obispo",
        "township": "Habana Vieja",
        "adress": "Obispo 415 Aguacate y Compostela",
        "local": "restaurante",
        "open": "12:00",
        "close": "22:00",
        "days_of_week": [
            "lunes",
            "martes",
            "miercoles",
            "jueves",
            "viernes",
            "sabado",
            "domingo"
        ],
        "sector": "estatal",
        "capability": 35,
        "social_network": [],
        "years": null
    },
    "economy": {
        "payment_methods": [
            "efectivo",
            "transferencia"
        ],
        "online_reservation": false,
        "tips_included": null,
        "delivery": false
    },
    "food": {
        "menu": {
            "appetizers": {
                "appetizers_list": [
                    "eperlan de pescado",
                    "croquetas de la casa"
                ],
                "appetizers_price": [
                    600,
                    250
                ]
            },
            "garnishes": {
                "garnishes_list": [],
                "garnishes_price": []
            },
            "hamburger": {
                "hamburger_list": [],
                "hamburger_price": []
            },
            "bread": {
                "bread_list": [],
                "bread_price": []
            },
            "main": {
                "main_list": [
                    "chuletas de cerdo",
                    "masas de cerdo",
                    "bistec de cerdo grille",
                    "fajitas de cerdo",
                    "lomo ahumado grille"
                ],
                "main_price": [
                    900,
                    900,
                    850,
                    850,
                    850
                ]
            },
            "sea_food": {
                "sea_food_list": [
                    "langosta grille",
                    "langosta enchilada",
                    "camaron grille",
                    "camaron enchilado",
                    "rueda de bonito grille",
                    "filete de pescado empanado",
                    "masas de pescado enchiladas"
                ],
                "sea_food_price": [
                    1200,
                    1200,
                    750,
                    750,
                    700,
                    800,
                    800
                ]
            },
            "pasta": {
                "pasta_list": [],
                "pasta_price": []
            },
            "pizza": {
                "pizza_list": [],
                "pizza_price": []
            },
            "adds": {
                "adds_list": [],
                "adds_price": []
            },
            "dessert": {
                "dessert_list": [],
                "dessert_price": []
            },
            "drinks": {
                "alcohol_list": [],
                "alcohol_price": [],
                "infusions_list": [],
                "infusions_price": [],
                "non_alcoholic_list": [],
                "non_alcoholic_price": []
                
            }
        },
        "popular_food": [],
        "popular_drink": [],
        "food_especialization": [
            "Criolla"
        ],
        "house_especiality": []
    },
    "social": {
        "kids_seat": true,
        "blackout_alternatives": null,
        "entertainment": [],
        "peak_hour": [],
        "tourism": null,
        "pets": false,
        "bathroom": null,
        "heated": null
    }
}